setup.py
proxy_utils/__init__.py
requests_proxy_utils.egg-info/PKG-INFO
requests_proxy_utils.egg-info/SOURCES.txt
requests_proxy_utils.egg-info/dependency_links.txt
requests_proxy_utils.egg-info/top_level.txt