Metadata-Version: 2.1
Name: requests-proxy-utils
Version: 0.0.3
Summary: A Library for using proxies with the requests library
Author: Leon
Author-email: leonwagner09@gmail.com
Keywords: python,first package
Classifier: Development Status :: 3 - Alpha
Classifier: Intended Audience :: Education
Classifier: Programming Language :: Python :: 3
Classifier: Operating System :: MacOS :: MacOS X
Classifier: Operating System :: Microsoft :: Windows
